{"7497106": {"page_count": 73, "depth": 0, "parent": null}, "47929297": {"page_count": 11, "depth": 1, "parent": "7497106"}, "5659398": {"page_count": 12, "depth": 2, "parent": 47929297}, "44083058": {"page_count": 13, "depth": 3, "parent": 5659398}, "41547883": {"page_count": 5, "depth": 3, "parent": 5659398}, "25292946": {"page_count": 8, "depth": 3, "parent": 5659398}, "50159885": {"page_count": 21, "depth": 3, "parent": 5659398}, "48410965": {"page_count": 26, "depth": 3, "parent": 5659398}, "61452059": {"page_count": 2, "depth": 3, "parent": 5659398}, "16663588": {"page_count": 57, "depth": 1, "parent": "7497106"}, "25578646": {"page_count": 102, "depth": 2, "parent": 16663588}, "42859469": {"page_count": 60, "depth": 3, "parent": 25578646}, "43684072": {"page_count": 3, "depth": 3, "parent": 25578646}, "719173": {"page_count": 257, "depth": 3, "parent": 25578646}, "51043243": {"page_count": 7, "depth": 2, "parent": 16663588}, "29105199": {"page_count": 2, "depth": 2, "parent": 16663588}, "51043259": {"page_count": 72, "depth": 2, "parent": 16663588}, "62322103": {"page_count": 54, "depth": 3, "parent": 51043259}, "38330568": {"page_count": 18, "depth": 1, "parent": "7497106"}, "2656140": {"page_count": 32, "depth": 2, "parent": 38330568}, "47477460": {"page_count": 1, "depth": 3, "parent": 2656140}, "1772720": {"page_count": 104, "depth": 1, "parent": "7497106"}, "24919263": {"page_count": 12, "depth": 2, "parent": 1772720}, "50769730": {"page_count": 0, "depth": 3, "parent": 24919263}, "1086458": {"page_count": 0, "depth": 3, "parent": 24919263}, "50769797": {"page_count": 0, "depth": 3, "parent": 24919263}, "61932769": {"page_count": 0, "depth": 3, "parent": 24919263}, "32973350": {"page_count": 14, "depth": 3, "parent": 24919263}, "50769888": {"page_count": 0, "depth": 3, "parent": 24919263}, "54049432": {"page_count": 13, "depth": 3, "parent": 24919263}, "46188412": {"page_count": 1, "depth": 3, "parent": 24919263}, "34403536": {"page_count": 4, "depth": 3, "parent": 24919263}, "56809761": {"page_count": 2, "depth": 3, "parent": 24919263}, "46188516": {"page_count": 0, "depth": 3, "parent": 24919263}, "41338830": {"page_count": 1, "depth": 3, "parent": 24919263}, "46187365": {"page_count": 4, "depth": 3, "parent": 24919263}, "46187419": {"page_count": 3, "depth": 3, "parent": 24919263}, "43514149": {"page_count": 6, "depth": 3, "parent": 24919263}, "46187398": {"page_count": 2, "depth": 3, "parent": 24919263}, "32612884": {"page_count": 5, "depth": 3, "parent": 24919263}, "46188487": {"page_count": 1, "depth": 3, "parent": 24919263}, "56035535": {"page_count": 2, "depth": 3, "parent": 24919263}, "46182889": {"page_count": 1, "depth": 3, "parent": 24919263}, "50188816": {"page_count": 0, "depth": 3, "parent": 24919263}, "46182786": {"page_count": 2, "depth": 3, "parent": 24919263}, "46182907": {"page_count": 4, "depth": 3, "parent": 24919263}, "48420186": {"page_count": 1, "depth": 3, "parent": 24919263}, "46182817": {"page_count": 3, "depth": 3, "parent": 24919263}, "62032025": {"page_count": 0, "depth": 3, "parent": 24919263}, "46187136": {"page_count": 5, "depth": 3, "parent": 24919263}, "41338994": {"page_count": 3, "depth": 3, "parent": 24919263}, "41339004": {"page_count": 2, "depth": 3, "parent": 24919263}, "46197538": {"page_count": 3, "depth": 3, "parent": 24919263}, "52822777": {"page_count": 1, "depth": 3, "parent": 24919263}, "17514014": {"page_count": 14, "depth": 3, "parent": 24919263}, "20192143": {"page_count": 35, "depth": 3, "parent": 24919263}, "30326850": {"page_count": 92, "depth": 2, "parent": 1772720}, "45437540": {"page_count": 16, "depth": 3, "parent": 30326850}, "31108863": {"page_count": 27, "depth": 3, "parent": 30326850}, "29672097": {"page_count": 38, "depth": 2, "parent": 1772720}, "34983781": {"page_count": 12, "depth": 3, "parent": 29672097}, "40858496": {"page_count": 4, "depth": 3, "parent": 29672097}, "24706219": {"page_count": 49, "depth": 3, "parent": 29672097}, "36692825": {"page_count": 6, "depth": 3, "parent": 29672097}, "24151121": {"page_count": 9, "depth": 3, "parent": 29672097}, "35576648": {"page_count": 22, "depth": 3, "parent": 29672097}, "50439669": {"page_count": 7, "depth": 3, "parent": 29672097}, "34563024": {"page_count": 8, "depth": 3, "parent": 29672097}, "31766846": {"page_count": 58, "depth": 2, "parent": 1772720}, "43573811": {"page_count": 24, "depth": 3, "parent": 31766846}, "65526406": {"page_count": 1, "depth": 3, "parent": 31766846}, "48246006": {"page_count": 4, "depth": 3, "parent": 31766846}, "33718304": {"page_count": 9, "depth": 3, "parent": 31766846}, "41297205": {"page_count": 22, "depth": 3, "parent": 31766846}, "42727838": {"page_count": 14, "depth": 3, "parent": 31766846}, "50437413": {"page_count": 1, "depth": 3, "parent": 31766846}, "42727558": {"page_count": 10, "depth": 3, "parent": 31766846}, "41035118": {"page_count": 27, "depth": 3, "parent": 31766846}, "8892640": {"page_count": 54, "depth": 2, "parent": 1772720}, "38263343": {"page_count": 15, "depth": 3, "parent": 8892640}, "35197345": {"page_count": 21, "depth": 3, "parent": 8892640}, "30197431": {"page_count": 9, "depth": 3, "parent": 8892640}, "31119092": {"page_count": 248, "depth": 3, "parent": 8892640}, "28085670": {"page_count": 29, "depth": 2, "parent": 1772720}, "691926": {"page_count": 20, "depth": 3, "parent": 28085670}, "21753440": {"page_count": 43, "depth": 3, "parent": 28085670}, "21116311": {"page_count": 24, "depth": 3, "parent": 28085670}, "1269702": {"page_count": 123, "depth": 3, "parent": 28085670}, "51303261": {"page_count": 23, "depth": 3, "parent": 28085670}, "34742345": {"page_count": 37, "depth": 3, "parent": 28085670}, "10477191": {"page_count": 60, "depth": 3, "parent": 28085670}, "28085738": {"page_count": 38, "depth": 3, "parent": 28085670}, "24909288": {"page_count": 69, "depth": 2, "parent": 1772720}, "870031": {"page_count": 55, "depth": 3, "parent": 24909288}, "1394400": {"page_count": 62, "depth": 3, "parent": 24909288}, "4784744": {"page_count": 13, "depth": 3, "parent": 24909288}, "26434943": {"page_count": 10, "depth": 3, "parent": 24909288}, "53971109": {"page_count": 11, "depth": 3, "parent": 24909288}, "1650557": {"page_count": 39, "depth": 3, "parent": 24909288}, "1391448": {"page_count": 38, "depth": 3, "parent": 24909288}, "27091933": {"page_count": 1, "depth": 3, "parent": 24909288}, "1391544": {"page_count": 17, "depth": 3, "parent": 24909288}, "1391398": {"page_count": 12, "depth": 3, "parent": 24909288}, "1047874": {"page_count": 4, "depth": 3, "parent": 24909288}, "974366": {"page_count": 21, "depth": 3, "parent": 24909288}, "1056777": {"page_count": 5, "depth": 3, "parent": 24909288}, "837363": {"page_count": 61, "depth": 3, "parent": 24909288}, "24909311": {"page_count": 8, "depth": 3, "parent": 24909288}, "718553": {"page_count": 67, "depth": 3, "parent": 24909288}, "1391604": {"page_count": 15, "depth": 3, "parent": 24909288}, "26445082": {"page_count": 108, "depth": 3, "parent": 24909288}, "39617423": {"page_count": 16, "depth": 3, "parent": 24909288}, "56516753": {"page_count": 5, "depth": 2, "parent": 1772720}, "23651738": {"page_count": 138, "depth": 3, "parent": 56516753}, "56516757": {"page_count": 1, "depth": 3, "parent": 56516753}, "6807993": {"page_count": 5, "depth": 2, "parent": 1772720}, "60576699": {"page_count": 0, "depth": 3, "parent": 6807993}, "44589755": {"page_count": 22, "depth": 3, "parent": 6807993}, "15091900": {"page_count": 19, "depth": 3, "parent": 6807993}, "30505394": {"page_count": 8, "depth": 3, "parent": 6807993}, "62630207": {"page_count": 1, "depth": 2, "parent": 1772720}, "4714210": {"page_count": 418, "depth": 3, "parent": 62630207}, "53368150": {"page_count": 63, "depth": 3, "parent": 62630207}, "60848077": {"page_count": 28, "depth": 3, "parent": 62630207}, "35712132": {"page_count": 29, "depth": 3, "parent": 62630207}, "53736194": {"page_count": 16, "depth": 3, "parent": 62630207}, "7852109": {"page_count": 244, "depth": 3, "parent": 62630207}, "10406353": {"page_count": 43, "depth": 2, "parent": 1772720}, "802101": {"page_count": 3, "depth": 3, "parent": 10406353}, "695886": {"page_count": 18, "depth": 3, "parent": 10406353}, "2084138": {"page_count": 49, "depth": 3, "parent": 10406353}, "6868072": {"page_count": 27, "depth": 3, "parent": 10406353}, "4401856": {"page_count": 22, "depth": 2, "parent": 1772720}, "5783724": {"page_count": 49, "depth": 2, "parent": 1772720}, "16798447": {"page_count": 74, "depth": 3, "parent": 5783724}, "6056685": {"page_count": 50, "depth": 3, "parent": 5783724}, "14573701": {"page_count": 12, "depth": 3, "parent": 5783724}, "59756363": {"page_count": 29, "depth": 3, "parent": 5783724}, "43259341": {"page_count": 13, "depth": 3, "parent": 5783724}, "55010859": {"page_count": 5, "depth": 3, "parent": 5783724}, "905874": {"page_count": 23, "depth": 3, "parent": 5783724}, "10032738": {"page_count": 25, "depth": 3, "parent": 5783724}, "27569302": {"page_count": 2, "depth": 3, "parent": 5783724}, "15979302": {"page_count": 27, "depth": 3, "parent": 5783724}, "47644627": {"page_count": 16, "depth": 2, "parent": 1772720}, "7532082": {"page_count": 24, "depth": 2, "parent": 1772720}, "32818016": {"page_count": 31, "depth": 3, "parent": 7532082}, "42812629": {"page_count": 47, "depth": 3, "parent": 7532082}, "43346850": {"page_count": 6, "depth": 1, "parent": "7497106"}, "17781731": {"page_count": 64, "depth": 2, "parent": 43346850}, "23518625": {"page_count": 20, "depth": 3, "parent": 17781731}, "34322033": {"page_count": 3, "depth": 3, "parent": 17781731}, "17781674": {"page_count": 42, "depth": 3, "parent": 17781731}, "31141790": {"page_count": 17, "depth": 3, "parent": 17781731}, "4438415": {"page_count": 10, "depth": 3, "parent": 17781731}, "9418715": {"page_count": 37, "depth": 1, "parent": "7497106"}, "36563433": {"page_count": 4, "depth": 1, "parent": "7497106"}, "22735582": {"page_count": 29, "depth": 1, "parent": "7497106"}, "20944360": {"page_count": 34, "depth": 2, "parent": 22735582}, "51793566": {"page_count": 4, "depth": 3, "parent": 20944360}, "38496501": {"page_count": 7, "depth": 3, "parent": 20944360}, "21232313": {"page_count": 5, "depth": 3, "parent": 20944360}, "6255189": {"page_count": 20, "depth": 3, "parent": 20944360}, "48370069": {"page_count": 37, "depth": 3, "parent": 20944360}, "37141189": {"page_count": 27, "depth": 2, "parent": 22735582}, "37666145": {"page_count": 10, "depth": 3, "parent": 37141189}, "41896330": {"page_count": 9, "depth": 3, "parent": 37141189}, "37182139": {"page_count": 20, "depth": 3, "parent": 37141189}, "37141294": {"page_count": 96, "depth": 3, "parent": 37141189}, "2640479": {"page_count": 58, "depth": 2, "parent": 22735582}, "38784141": {"page_count": 0, "depth": 3, "parent": 2640479}, "31941249": {"page_count": 0, "depth": 3, "parent": 2640479}, "55947848": {"page_count": 7, "depth": 3, "parent": 2640479}, "1275386": {"page_count": 29, "depth": 3, "parent": 2640479}, "37660261": {"page_count": 6, "depth": 3, "parent": 2640479}, "2157573": {"page_count": 17, "depth": 3, "parent": 2640479}, "31934898": {"page_count": 0, "depth": 3, "parent": 2640479}, "742485": {"page_count": 61, "depth": 3, "parent": 2640479}, "768946": {"page_count": 48, "depth": 3, "parent": 2640479}, "1210959": {"page_count": 11, "depth": 3, "parent": 2640479}, "803992": {"page_count": 23, "depth": 3, "parent": 2640479}, "62242833": {"page_count": 6, "depth": 3, "parent": 2640479}, "37900531": {"page_count": 7, "depth": 3, "parent": 2640479}, "43949321": {"page_count": 9, "depth": 3, "parent": 2640479}, "50004186": {"page_count": 3, "depth": 3, "parent": 2640479}, "31880544": {"page_count": 29, "depth": 2, "parent": 22735582}, "1063984": {"page_count": 29, "depth": 3, "parent": 31880544}, "51151274": {"page_count": 0, "depth": 3, "parent": 31880544}, "22702482": {"page_count": 12, "depth": 3, "parent": 31880544}, "5575394": {"page_count": 140, "depth": 3, "parent": 31880544}, "39570219": {"page_count": 14, "depth": 3, "parent": 31880544}, "54309578": {"page_count": 10, "depth": 1, "parent": "7497106"}}